faker_vehicle/__init__.py
faker_vehicle/machine_dict.py
faker_vehicle/vehicle_dict.py
faker_vehicle-0.2.0.dist-info/LICENSE
faker_vehicle-0.2.0.dist-info/METADATA
faker_vehicle-0.2.0.dist-info/WHEEL
faker_vehicle-0.2.0.dist-info/top_level.txt
faker_vehicle-0.2.0.dist-info/zip-safe
faker_vehicle-0.2.0.dist-info/RECORD
