Metadata-Version: 1.1
Name: faker-vehicle
Version: 0.2.0
Summary: Vehicle related Provider for the Faker Python package.
Home-page: https://github.com/kennethwsmith/faker_vehicle
Author: kennethwsmith
Author-email: kennethwsmith+fakerveh@gmail.com
License: Apache License, Version 2.0
Keywords: faker vehicle test data
Platform: any
Classifier: Development Status :: 4 - Beta
Classifier: Environment :: Console
Classifier: Intended Audience :: Developers
Classifier: Programming Language :: Python
Classifier: Programming Language :: Python :: 3
Classifier: Programming Language :: Python :: 3.4
Classifier: Programming Language :: Python :: 3.5
Classifier: Programming Language :: Python :: 3.6
Classifier: Programming Language :: Python :: 3.7
Classifier: Programming Language :: Python :: Implementation :: PyPy
Classifier: Topic :: Software Development :: Libraries :: Python Modules
Classifier: Topic :: Software Development :: Testing
Classifier: Topic :: Utilities
Classifier: License :: OSI Approved :: Apache Software License
